mirror_to_s3/archiver.py
mirror_to_s3/pyproject.toml
mirror_to_s3-0.0.2.dist-info/licenses/LICENSE
mirror_to_s3-0.0.2.dist-info/METADATA
mirror_to_s3-0.0.2.dist-info/WHEEL
mirror_to_s3-0.0.2.dist-info/entry_points.txt
mirror_to_s3-0.0.2.dist-info/top_level.txt
mirror_to_s3-0.0.2.dist-info/RECORD
