Metadata-Version: 2.4
Name: mirror_to_s3
Version: 0.0.2
Summary: mirror-to-S3 - mirror an index page into an S3 bucket
Author-email: Dale Magee <mirror2s3@antisol.org>
License-Expression: BSD-3-Clause
Project-URL: Homepage, https://gitlab.com/AntiSol/mirror_to_s3
Project-URL: Bug Tracker, https://gitlab.com/AntiSol/mirror_to_s3/-/issues
Classifier: Development Status :: 4 - Beta
Classifier: Intended Audience :: Developers
Classifier: Programming Language :: Python :: 3
Classifier: Operating System :: OS Independent
Requires-Python: >=3.11
License-File: LICENSE
Requires-Dist: httpx
Requires-Dist: httpx-retries
Requires-Dist: aiofiles
Requires-Dist: aioboto3
Requires-Dist: pyyaml
Requires-Dist: python-dotenv
Requires-Dist: lxml
Dynamic: license-file
